pylinearalg/__init__.py
pylinearalg/gram_schmidt.py
pylinearalg/vector.py
pylinearalg-0.2.0.dist-info/WHEEL
pylinearalg-0.2.0.dist-info/METADATA
pylinearalg-0.2.0.dist-info/RECORD
