Metadata-Version: 2.1
Name: pylinearalg
Version: 0.2.0
Summary: 
Author: Thomas Breydo
Author-email: tbreydo@gmail.com
Requires-Python: >=3.10,<4.0
Classifier: Programming Language :: Python :: 3
Classifier: Programming Language :: Python :: 3.10
Requires-Dist: sympy (>=1.9,<2.0)
